{
  "showGettingStartedBanner": true,
  "hasMigratedDailyNoteSettings": false,
  "hasMigratedWeeklyNoteSettings": false,
  "daily": {
    "format": "",
    "template": "templates/okr/Daily.md",
    "folder": "notes/okr/daily",
    "enabled": true
  },
  "weekly": {
    "format": "",
    "template": "templates/okr/Weekly Review.md",
    "folder": "notes/okr/weekly",
    "enabled": true
  },
  "monthly": {
    "format": "",
    "template": "templates/okr/Monthly Review.md",
    "folder": "notes/okr/monthly",
    "enabled": true
  },
  "quarterly": {
    "format": "",
    "template": "",
    "folder": "",
    "enabled": false
  },
  "yearly": {
    "format": "",
    "template": "",
    "folder": ""
  }
}